Metadata-Version: 2.1
Name: auto_clicks
Version: 1.0
Summary: A quick Linker
Home-page: UNKNOWN
Author: lin_zhe
Author-email: mcwyzlele@163.com
License: MIT License
Platform: any
